setup.py
agent/__init__.py
agent/agent.py
agent/log.py
agent/utils.py
agent/backends/__init__.py
agent/backends/send_tele.py
api/__init__.py
api/client.py
api/log_handler.py
telegram_flylog.egg-info/PKG-INFO
telegram_flylog.egg-info/SOURCES.txt
telegram_flylog.egg-info/dependency_links.txt
telegram_flylog.egg-info/requires.txt
telegram_flylog.egg-info/top_level.txt