Metadata-Version: 1.0
Name: telegram-flylog
Version: 0.0.2
Summary: 基于flylog的telegram日志发送
Home-page: https://github.com/deanzhou69/telegram_log
Author: dean
Author-email: deanzhou56@gmail.com
License: UNKNOWN
Platform: UNKNOWN
